send_sms/__init__.py
send_sms/send.py
send_notif-0.1.dist-info/LICENSE
send_notif-0.1.dist-info/METADATA
send_notif-0.1.dist-info/WHEEL
send_notif-0.1.dist-info/top_level.txt
send_notif-0.1.dist-info/RECORD
